phasik/__init__.py
phasik/_version.py
phasik/classes/DistanceMatrix.py
phasik/classes/PartiallyTemporalNetwork.py
phasik/classes/TemporalData.py
phasik/classes/TemporalNetwork.py
phasik/classes/__init__.py
phasik/classes/clustering/ClusterSet.py
phasik/classes/clustering/ClusterSets.py
phasik/classes/clustering/__init__.py
phasik/drawing/__init__.py
phasik/drawing/drawing.py
phasik/drawing/drawing_clusters.py
phasik/drawing/drawing_networks.py
phasik/drawing/utils.py
phasik/utils/__init__.py
phasik/utils/clusters.py
phasik/utils/convert.py
phasik/utils/graphs.py
phasik/utils/paths.py
phasik/utils/utils.py
phasik/utils/xppcall.py
phasik-1.3.4.dist-info/LICENSE
phasik-1.3.4.dist-info/METADATA
phasik-1.3.4.dist-info/WHEEL
phasik-1.3.4.dist-info/top_level.txt
phasik-1.3.4.dist-info/RECORD
